propfill/__init__.py
propfill/_proportional_imputer.py
sklearn_propfill-0.1.0.dist-info/licenses/LICENSE
sklearn_propfill-0.1.0.dist-info/METADATA
sklearn_propfill-0.1.0.dist-info/WHEEL
sklearn_propfill-0.1.0.dist-info/top_level.txt
sklearn_propfill-0.1.0.dist-info/RECORD
