Metadata-Version: 2.4
Name: sklearn-propfill
Version: 0.1.0
Summary: A scikit-learn compatible transformer for proportional categorical imputation.
Author: Your Name
License: MIT
Requires-Python: >=3.9
License-File: LICENSE
Requires-Dist: numpy>=1.22
Requires-Dist: pandas>=1.5
Requires-Dist: scikit-learn>=1.2
Provides-Extra: dev
Requires-Dist: pytest>=7; extra == "dev"
Requires-Dist: ruff>=0.4; extra == "dev"
Requires-Dist: black>=24.0; extra == "dev"
Dynamic: license-file
